concept_x_converter-0.3.7.dist-info/METADATA
concept_x_converter-0.3.7.dist-info/WHEEL
concept_x_converter/__init__.py
concept_x_converter/concept_x_converter.abi3.so
concept_x_converter-0.3.7.dist-info/RECORD
