Metadata-Version: 2.1
Name: concept_x_converter
Version: 0.3.7
